suisa_sendemeldung/__init__.py
suisa_sendemeldung/acrclient.py
suisa_sendemeldung/suisa_sendemeldung.py
suisa_sendemeldung-0.17.0.dist-info/METADATA
suisa_sendemeldung-0.17.0.dist-info/WHEEL
suisa_sendemeldung-0.17.0.dist-info/entry_points.txt
suisa_sendemeldung-0.17.0.dist-info/licenses/LICENSE
suisa_sendemeldung-0.17.0.dist-info/RECORD
