Metadata-Version: 2.4
Name: suisa_sendemeldung
Version: 0.17.0
Summary: ACRCloud client for SUISA reporting
License: MIT
License-File: LICENSE
Author: RaBe IT-Reaktion
Author-email: it@rabe.ch
Requires-Python: >=3.12,<4.0
Classifier: License :: OSI Approved :: MIT License
Classifier: Programming Language :: Python :: 3
Classifier: Programming Language :: Python :: 3.12
Classifier: Programming Language :: Python :: 3.13
Classifier: Programming Language :: Python :: 3.14
Requires-Dist: Babel (>=2.12.1,<3.0.0)
Requires-Dist: ConfigArgParse (>=1.5.5,<2.0.0)
Requires-Dist: acrclient (>=0.4.4,<0.6.0)
Requires-Dist: dateutils (>=0.6.12,<0.7.0)
Requires-Dist: iso3901 (>=0.3,<1.2)
Requires-Dist: openpyxl (>=3.1.2,<4.0.0)
Requires-Dist: pytz (>=2023.3,<2026.0)
Requires-Dist: rabe-cridlib (>=0.12.0,<0.14.0)
Requires-Dist: requests (>=2.31.0,<3.0.0)
Requires-Dist: tqdm (>=4.65.0,<5.0.0)
Project-URL: Repository, http://github.com/radiorabe/suisa_reporting
